trio_scgi/__init__.py
trio_scgi-0.2.0.dist-info/DESCRIPTION.rst
trio_scgi-0.2.0.dist-info/METADATA
trio_scgi-0.2.0.dist-info/RECORD
trio_scgi-0.2.0.dist-info/WHEEL
trio_scgi-0.2.0.dist-info/metadata.json
trio_scgi-0.2.0.dist-info/top_level.txt
trio_scgi-0.2.0.dist-info/zip-safe
