Metadata-Version: 2.0
Name: trio-scgi
Version: 0.2.0
Summary: SCGI implementation based on Trio
Home-page: https://github.com/joernheissler/trio-scgi/
Author: Jörn Heissler
License: MIT
Keywords: trio,scgi
Platform: UNKNOWN
Classifier: Development Status :: 4 - Beta
Classifier: License :: OSI Approved :: MIT License
Classifier: Intended Audience :: Developers
Classifier: Programming Language :: Python :: 3.5
Classifier: Programming Language :: Python :: 3.6
Classifier: Programming Language :: Python :: 3.7
Requires-Python: >= 3.5.3
Requires-Dist: multidict
Requires-Dist: trio
